{
    "key": "group_66b8cc4ad5edb",
    "title": "Initial block",
    "fields": [
        {
            "key": "field_66b8cc9affaef",
            "label": "Background",
            "name": "bg",
            "type": "select",
            "instructions": "",
            "required": 0,
            "conditional_logic": 0,
            "wrapper": {
                "width": "",
                "class": "",
                "id": ""
            },
            "choices": {
                "gold": "gold",
                "red": "red",
                "green": "green",
                "blue": "blue"
            },
            "default_value": false,
            "return_format": "value",
            "multiple": 0,
            "allow_null": 0,
            "ui": 0,
            "ajax": 0,
            "placeholder": ""
        },
        {
            "key": "field_66b8cc4bf767a",
            "label": "Team",
            "name": "team",
            "type": "repeater",
            "instructions": "",
            "required": 0,
            "conditional_logic": 0,
            "wrapper": {
                "width": "",
                "class": "",
                "id": ""
            },
            "layout": "block",
            "pagination": 0,
            "min": 0,
            "max": 0,
            "collapsed": "",
            "button_label": "Add Row",
            "rows_per_page": 20,
            "sub_fields": [
                {
                    "key": "field_66b8cc67f767b",
                    "label": "Image",
                    "name": "image",
                    "type": "image",
                    "instructions": "",
                    "required": 0,
                    "conditional_logic": 0,
                    "wrapper": {
                        "width": "",
                        "class": "",
                        "id": ""
                    },
                    "return_format": "id",
                    "library": "all",
                    "min_width": "",
                    "min_height": "",
                    "min_size": "",
                    "max_width": "",
                    "max_height": "",
                    "max_size": "",
                    "mime_types": "",
                    "preview_size": "medium",
                    "parent_repeater": "field_66b8cc4bf767a"
                },
                {
                    "key": "field_66b8cc79f767c",
                    "label": "Name",
                    "name": "name",
                    "type": "text",
                    "instructions": "",
                    "required": 0,
                    "conditional_logic": 0,
                    "wrapper": {
                        "width": "",
                        "class": "",
                        "id": ""
                    },
                    "default_value": "",
                    "maxlength": "",
                    "placeholder": "",
                    "prepend": "",
                    "append": "",
                    "parent_repeater": "field_66b8cc4bf767a"
                },
                {
                    "key": "field_66b8cc7ef767d",
                    "label": "HTML",
                    "name": "html",
                    "type": "wysiwyg",
                    "instructions": "",
                    "required": 0,
                    "conditional_logic": 0,
                    "wrapper": {
                        "width": "",
                        "class": "",
                        "id": ""
                    },
                    "default_value": "",
                    "delay": 0,
                    "tabs": "all",
                    "toolbar": "full",
                    "media_upload": 1,
                    "parent_repeater": "field_66b8cc4bf767a"
                }
            ]
        }
    ],
    "location": [
        [
            {
                "param": "block",
                "operator": "==",
                "value": "skeleton-core\/initial"
            }
        ]
    ],
    "menu_order": 0,
    "position": "normal",
    "style": "default",
    "label_placement": "top",
    "instruction_placement": "label",
    "hide_on_screen": "",
    "active": true,
    "description": "",
    "show_in_rest": 0,
    "modified": 1723387100
}